guiwithxml/__init__.py
guiwithxml/elements.py
guiwithxml/exceptions.py
guiwithxml/parser.py
guiwithxml/rerender.py
guiwithxml-0.1.1.dist-info/licenses/LICENSE
guiwithxml-0.1.1.dist-info/METADATA
guiwithxml-0.1.1.dist-info/WHEEL
guiwithxml-0.1.1.dist-info/top_level.txt
guiwithxml-0.1.1.dist-info/RECORD
