Metadata-Version: 2.4
Name: guiwithxml
Version: 0.1.1
Summary: XML kullanarak özel Tkinter arayüzleri çizen bir kütüphane.
Author-email: Adınız Soyadınız <email@adresiniz.com>
Classifier: Programming Language :: Python :: 3
Classifier: License :: OSI Approved :: MIT License
Classifier: Operating System :: OS Independent
Requires-Python: >=3.8
License-File: LICENSE
Dynamic: license-file
